autopm/__init__.py
autopm/cli.py
autopm/tracker.py
autopm-0.1.1.dist-info/METADATA
autopm-0.1.1.dist-info/WHEEL
autopm-0.1.1.dist-info/entry_points.txt
autopm-0.1.1.dist-info/top_level.txt
autopm-0.1.1.dist-info/RECORD
